{"nodes": [{"id": "d_projects_aitrader_landing_contributing_md", "label": "CONTRIBUTING.md", "file_type": "document", "source_file": "D:\\projects\\aitrader-landing\\CONTRIBUTING.md", "source_location": "L1"}, {"id": "aitrader_landing_contributing_contributing_to_alpha_suite_strat", "label": "Contributing to Alpha Suite (Strat)", "file_type": "document", "source_file": "D:\\projects\\aitrader-landing\\CONTRIBUTING.md", "source_location": "L1"}, {"id": "aitrader_landing_contributing_1_codebase_architecture", "label": "1. Codebase Architecture", "file_type": "document", "source_file": "D:\\projects\\aitrader-landing\\CONTRIBUTING.md", "source_location": "L7"}, {"id": "aitrader_landing_contributing_2_development_workflow", "label": "2. Development Workflow", "file_type": "document", "source_file": "D:\\projects\\aitrader-landing\\CONTRIBUTING.md", "source_location": "L22"}, {"id": "aitrader_landing_contributing_step_1_clone_and_infrastructure", "label": "Step 1: Clone and Infrastructure", "file_type": "document", "source_file": "D:\\projects\\aitrader-landing\\CONTRIBUTING.md", "source_location": "L24"}, {"id": "aitrader_landing_contributing_codeblock_1", "label": "code:bash (docker-compose up -d)", "file_type": "document", "source_file": "D:\\projects\\aitrader-landing\\CONTRIBUTING.md", "source_location": "L26"}, {"id": "aitrader_landing_contributing_step_2_running_in_test_mode", "label": "Step 2: Running in Test Mode", "file_type": "document", "source_file": "D:\\projects\\aitrader-landing\\CONTRIBUTING.md", "source_location": "L31"}, {"id": "aitrader_landing_contributing_codeblock_2", "label": "code:bash (ALPHA_TEST_MODE=true)", "file_type": "document", "source_file": "D:\\projects\\aitrader-landing\\CONTRIBUTING.md", "source_location": "L33"}, {"id": "aitrader_landing_contributing_step_3_run_order", "label": "Step 3: Run Order", "file_type": "document", "source_file": "D:\\projects\\aitrader-landing\\CONTRIBUTING.md", "source_location": "L38"}, {"id": "aitrader_landing_contributing_3_git_rules_branching", "label": "3. Git Rules & Branching", "file_type": "document", "source_file": "D:\\projects\\aitrader-landing\\CONTRIBUTING.md", "source_location": "L48"}, {"id": "aitrader_landing_contributing_4_code_quality_standards", "label": "4. Code Quality & Standards", "file_type": "document", "source_file": "D:\\projects\\aitrader-landing\\CONTRIBUTING.md", "source_location": "L65"}, {"id": "aitrader_landing_contributing_secrets_and_api_keys", "label": "Secrets and API Keys", "file_type": "document", "source_file": "D:\\projects\\aitrader-landing\\CONTRIBUTING.md", "source_location": "L67"}, {"id": "aitrader_landing_contributing_rust_style", "label": "Rust Style", "file_type": "document", "source_file": "D:\\projects\\aitrader-landing\\CONTRIBUTING.md", "source_location": "L72"}, {"id": "aitrader_landing_contributing_typescript_next_js_css_style", "label": "TypeScript / Next.js / CSS Style", "file_type": "document", "source_file": "D:\\projects\\aitrader-landing\\CONTRIBUTING.md", "source_location": "L77"}, {"id": "aitrader_landing_contributing_5_reporting_issues_feedback", "label": "5. Reporting Issues & Feedback", "file_type": "document", "source_file": "D:\\projects\\aitrader-landing\\CONTRIBUTING.md", "source_location": "L86"}], "edges": [{"source": "d_projects_aitrader_landing_contributing_md", "target": "aitrader_landing_contributing_contributing_to_alpha_suite_strat", "relation": "contains", "confidence": "EXTRACTED", "source_file": "D:\\projects\\aitrader-landing\\CONTRIBUTING.md", "source_location": "L1", "weight": 1.0}, {"source": "aitrader_landing_contributing_contributing_to_alpha_suite_strat", "target": "aitrader_landing_contributing_1_codebase_architecture", "relation": "contains", "confidence": "EXTRACTED", "source_file": "D:\\projects\\aitrader-landing\\CONTRIBUTING.md", "source_location": "L7", "weight": 1.0}, {"source": "aitrader_landing_contributing_contributing_to_alpha_suite_strat", "target": "aitrader_landing_contributing_2_development_workflow", "relation": "contains", "confidence": "EXTRACTED", "source_file": "D:\\projects\\aitrader-landing\\CONTRIBUTING.md", "source_location": "L22", "weight": 1.0}, {"source": "aitrader_landing_contributing_2_development_workflow", "target": "aitrader_landing_contributing_step_1_clone_and_infrastructure", "relation": "contains", "confidence": "EXTRACTED", "source_file": "D:\\projects\\aitrader-landing\\CONTRIBUTING.md", "source_location": "L24", "weight": 1.0}, {"source": "aitrader_landing_contributing_step_1_clone_and_infrastructure", "target": "aitrader_landing_contributing_codeblock_1", "relation": "contains", "confidence": "EXTRACTED", "source_file": "D:\\projects\\aitrader-landing\\CONTRIBUTING.md", "source_location": "L26", "weight": 1.0}, {"source": "aitrader_landing_contributing_2_development_workflow", "target": "aitrader_landing_contributing_step_2_running_in_test_mode", "relation": "contains", "confidence": "EXTRACTED", "source_file": "D:\\projects\\aitrader-landing\\CONTRIBUTING.md", "source_location": "L31", "weight": 1.0}, {"source": "aitrader_landing_contributing_step_2_running_in_test_mode", "target": "aitrader_landing_contributing_codeblock_2", "relation": "contains", "confidence": "EXTRACTED", "source_file": "D:\\projects\\aitrader-landing\\CONTRIBUTING.md", "source_location": "L33", "weight": 1.0}, {"source": "aitrader_landing_contributing_2_development_workflow", "target": "aitrader_landing_contributing_step_3_run_order", "relation": "contains", "confidence": "EXTRACTED", "source_file": "D:\\projects\\aitrader-landing\\CONTRIBUTING.md", "source_location": "L38", "weight": 1.0}, {"source": "aitrader_landing_contributing_contributing_to_alpha_suite_strat", "target": "aitrader_landing_contributing_3_git_rules_branching", "relation": "contains", "confidence": "EXTRACTED", "source_file": "D:\\projects\\aitrader-landing\\CONTRIBUTING.md", "source_location": "L48", "weight": 1.0}, {"source": "aitrader_landing_contributing_contributing_to_alpha_suite_strat", "target": "aitrader_landing_contributing_4_code_quality_standards", "relation": "contains", "confidence": "EXTRACTED", "source_file": "D:\\projects\\aitrader-landing\\CONTRIBUTING.md", "source_location": "L65", "weight": 1.0}, {"source": "aitrader_landing_contributing_4_code_quality_standards", "target": "aitrader_landing_contributing_secrets_and_api_keys", "relation": "contains", "confidence": "EXTRACTED", "source_file": "D:\\projects\\aitrader-landing\\CONTRIBUTING.md", "source_location": "L67", "weight": 1.0}, {"source": "aitrader_landing_contributing_4_code_quality_standards", "target": "aitrader_landing_contributing_rust_style", "relation": "contains", "confidence": "EXTRACTED", "source_file": "D:\\projects\\aitrader-landing\\CONTRIBUTING.md", "source_location": "L72", "weight": 1.0}, {"source": "aitrader_landing_contributing_4_code_quality_standards", "target": "aitrader_landing_contributing_typescript_next_js_css_style", "relation": "contains", "confidence": "EXTRACTED", "source_file": "D:\\projects\\aitrader-landing\\CONTRIBUTING.md", "source_location": "L77", "weight": 1.0}, {"source": "aitrader_landing_contributing_contributing_to_alpha_suite_strat", "target": "aitrader_landing_contributing_5_reporting_issues_feedback", "relation": "contains", "confidence": "EXTRACTED", "source_file": "D:\\projects\\aitrader-landing\\CONTRIBUTING.md", "source_location": "L86", "weight": 1.0}], "input_tokens": 0, "output_tokens": 0}